Verilog/DAY5/4_bit_down_counter/counter_async/down_counter.v
module down_counter (
    input clk,         
    input reset,       
   output reg [3:0] count
);

always @(posedge clk or posedge reset) begin
    if (reset)
        count <= 4'b1111;   
    else
        count <= count - 1; 
end

endmodule

Verilog/DAY5/4_bit_down_counter/counter_async/down_counter_tb.v
module down_counter_tb;

    reg clk, reset;
    wire [3:0] count;

    
    down_counter uut (
        .clk(clk),
        .reset(reset),
        .count(count)
    );

   
    initial begin
        clk = 0;
        forever #5 clk = ~clk;
    end

   
    initial begin
        $dumpfile("down_counter.vcd");
        $dumpvars(0, down_counter_tb);

        $monitor("Time=%0t | reset=%b | count=%b", $time, reset, count);

        reset = 1; #10;   
        reset = 0; #100;       
        $finish;
    end

endmodule

Verilog/DAY5/4_bit_down_counter/counter_sync/down_counter.vcd
$date
	Tue Sep 16 03:19:12 2025
$end
$version
	Icarus Verilog
$end
$timescale
	1s
$end
$scope module down_counter_tb $end
$var wire 4 ! count [3:0] $end
$var reg 1 " clk $end
$var reg 1 # reset $end
$scope module uut $end
$var wire 1 " clk $end
$var wire 1 # reset $end
$var reg 4 $ count [3:0] $end
$upscope $end
$upscope $end
$enddefinitions $end
$comment Show the parameter values. $end
$dumpall
$end
#0
$dumpvars
b1111 $
1#
0"
b1111 !
$end
#5
1"
#10
0"
0#
#15
b1110 !
b1110 $
1"
#20
0"
#25
b1101 !
b1101 $
1"
#30
0"
#35
b1100 !
b1100 $
1"
#40
0"
#45
b1011 !
b1011 $
1"
#50
0"
#55
b1010 !
b1010 $
1"
#60
0"
#65
b1001 !
b1001 $
1"
#70
0"
#75
b1000 !
b1000 $
1"
#80
0"
#85
b111 !
b111 $
1"
#90
0"
#95
b110 !
b110 $
1"
#100
0"
#105
b101 !
b101 $
1"
