Verilog/DAY4/5. D_LATCH/DLatch.v
module DLatch (
	input wire d,    
	input wire en,   
	output reg q     
);
	always @(*) begin
		if (en)
			q = d;        
	end
endmodule

Verilog/DAY4/5. D_LATCH/tb_DLatch.v
module tb_DLatch;
	reg d, en;
	wire q;

	DLatch uut (
 		.d(d),
		.en(en),
		.q(q)
	);
	
	initial begin
		$dumpfile("DLatch.vcd");
		$dumpvars(0,tb_DLatch);

		$monitor("Time=%0t | d=%b en=%b q=%b", $time, d, en, q);

		d = 0; en = 0;
		#10 en = 0; d = 1;   
		#10 d = 0;           
		#10 en = 1; d = 1;   
		#10 d = 0;           
		#10 en = 0; d = 1;   
		#10 en = 1; d = 0;   
		#10 d = 1;           

		#20 $finish;
	end
endmodule

Verilog/DAY4/5. D_LATCH/DLatch.vcd
$date
	Mon Sep 22 23:58:53 2025
$end
$version
	Icarus Verilog
$end
$timescale
	1s
$end
$scope module tb_DLatch $end
$var wire 1 ! q $end
$var reg 1 " d $end
$var reg 1 # en $end
$scope module uut $end
$var wire 1 " d $end
$var wire 1 # en $end
$var reg 1 ! q $end
$upscope $end
$upscope $end
$enddefinitions $end
$comment Show the parameter values. $end
$dumpall
$end
#0
$dumpvars
0#
0"
x!
$end
#10
1"
#20
0"
#30
1!
1"
1#
#40
0!
0"
#50
1"
0#
#60
0"
1#
#70
1!
1"
