Verilog/DAY3/Behavioral Modeling/2to1_mux/mux2to1_beh.v
module mux2to1_beh(
	input i0,    
	input i1,    
	input sel,   
	output reg y 
);

	always @(*) begin
        
	if(sel == 0) 
            y = i0; 
        else 
            y = i1; 
    end
endmodule

Verilog/DAY3/Behavioral Modeling/2to1_mux/mux2to1_tb.v
`timescale 1ns/1ps

module mux2to1_tb;
    reg i0, i1, sel;
    wire y;

    mux2to1_beh uut (
        .i0(i0),
        .i1(i1),
        .sel(sel),
        .y(y)
    );

    initial begin

        $dumpfile("mux2to1.vcd");
        $dumpvars(0, mux2to1_tb);

        $monitor("Time=%0t | i0=%b i1=%b sel=%b | y=%b", $time, i0, i1, sel, y);

        i0=0; i1=0; sel=0; #10;
        i0=0; i1=1; sel=0; #10;
        i0=1; i1=0; sel=0; #10;
        i0=1; i1=1; sel=0; #10;
        i0=0; i1=0; sel=1; #10;
        i0=0; i1=1; sel=1; #10;
        i0=1; i1=0; sel=1; #10;
        i0=1; i1=1; sel=1; #10;

        $finish; 
    end
endmodule

Verilog/DAY3/Behavioral Modeling/2to1_mux/mux2to1.vcd
$date
	Tue Sep  9 07:04:25 2025
$end
$version
	Icarus Verilog
$end
$timescale
	1ps
$end
$scope module mux2to1_tb $end
$var wire 1 ! y $end
$var reg 1 " i0 $end
$var reg 1 # i1 $end
$var reg 1 $ sel $end
$scope module uut $end
$var wire 1 " i0 $end
$var wire 1 # i1 $end
$var wire 1 $ sel $end
$var reg 1 ! y $end
$upscope $end
$upscope $end
$enddefinitions $end
$comment Show the parameter values. $end
$dumpall
$end
#0
$dumpvars
0$
0#
0"
0!
$end
#10000
1#
#20000
1!
0#
1"
#30000
1#
#40000
0!
1$
0#
0"
#50000
1!
1#
#60000
0!
0#
1"
#70000
1!
1#
