Verilog/DAY5/4_bit_SISO_register/register_sync/siso.v
module siso (
    input clk,          
    input reset,        
    input serial_in,    
    output serial_out   
);

    reg [3:0] shift_reg;  

    always @(posedge clk) begin
        if (reset)
            shift_reg <= 4'b0000;                 
        else
            shift_reg <= {shift_reg[2:0], serial_in}; 
    end

    assign serial_out = shift_reg[3]; 

endmodule

Verilog/DAY5/4_bit_SISO_register/register_sync/tb_siso.v
module tb_siso();

    reg clk;
    reg reset;
    reg serial_in;
    wire serial_out;

    siso uut (
        .clk(clk),
        .reset(reset),
        .serial_in(serial_in),
        .serial_out(serial_out)
    );


    initial begin
        clk = 0;
        forever #5 clk = ~clk;  
    end


    initial begin

        $dumpfile("siso.vcd");
        $dumpvars(0, tb_siso);

	$display("Time\t clk reset serial_in serial_out");
	$monitor("%0t\t %b  %b  %b  %b", $time, clk, reset, serial_in, serial_out);
        reset = 1;
        serial_in = 0;
        #10;
        
        reset = 0; 

        serial_in = 1; #10;
        serial_in = 0; #10;
        serial_in = 1; #10;
        serial_in = 1; #10;
        serial_in = 0; #10;
        serial_in = 1; #10;


        #50;
        $finish;
    end

endmodule

Verilog/DAY5/4_bit_SISO_register/register_sync/siso.vcd
$date
	Tue Sep 16 06:46:33 2025
$end
$version
	Icarus Verilog
$end
$timescale
	1s
$end
$scope module tb_siso $end
$var wire 1 ! serial_out $end
$var reg 1 " clk $end
$var reg 1 # reset $end
$var reg 1 $ serial_in $end
$scope module uut $end
$var wire 1 " clk $end
$var wire 1 # reset $end
$var wire 1 $ serial_in $end
$var wire 1 ! serial_out $end
$var reg 4 % shift_reg [3:0] $end
$upscope $end
$upscope $end
$enddefinitions $end
$comment Show the parameter values. $end
$dumpall
$end
#0
$dumpvars
bx %
0$
1#
0"
x!
$end
#5
0!
b0 %
1"
#10
0"
1$
0#
#15
b1 %
1"
#20
0"
0$
#25
b10 %
1"
#30
0"
1$
#35
b101 %
1"
#40
0"
#45
1!
b1011 %
1"
#50
0"
0$
#55
0!
b110 %
1"
#60
0"
1$
#65
1!
b1101 %
1"
#70
0"
#75
b1011 %
1"
#80
0"
#85
0!
b111 %
1"
#90
0"
#95
1!
b1111 %
1"
