Verilog/ASSIGNMENTS/Assignment1/Tristate 2:1 MUX/tri_2to1_mux.v
module tri_2to1_mux(a,b,o,s);
	input a,b,s;
	output o;
	bufif0(o,a,s);
	bufif1(o,b,s);
endmodule

Verilog/ASSIGNMENTS/Assignment1/Tristate 2:1 MUX/tb_tri_2to1_mux.v
module tb_tri_2to1_mux;
reg a,b,s;
wire o;
tri_2to1_mux uut( .a(a), .b(b), .s(s), .o(o));
initial begin
	$dumpfile("tri_mux2to1.vcd");
	$dumpvars(0, tb_tri_2to1_mux);
	$display("Time : s : a  b : o ");
	$monitor("%0t  : %b: %b %b : %b",$time,s,a,b,o);
	s=0; a=0; b=0;#10;
	s=0; a=0; b=1;#10;
	s=0; a=1; b=0;#10;
	s=0; a=1; b=1;#10;
        s=1; a=0; b=0;#10;
	s=1; a=0; b=1;#10;
	s=1; a=1; b=0;#10;
	s=1; a=1; b=1;#10;
$finish;
end
endmodule

Verilog/ASSIGNMENTS/Assignment1/Tristate 2:1 MUX/tri_mux2to1.vcd
$date
	Fri Sep  5 17:29:52 2025
$end
$version
	Icarus Verilog
$end
$timescale
	1s
$end
$scope module tb_tri_2to1_mux $end
$var wire 1 ! o $end
$var reg 1 " a $end
$var reg 1 # b $end
$var reg 1 $ s $end
$scope module uut $end
$var wire 1 " a $end
$var wire 1 # b $end
$var wire 1 ! o $end
$var wire 1 $ s $end
$upscope $end
$upscope $end
$enddefinitions $end
$comment Show the parameter values. $end
$dumpall
$end
#0
$dumpvars
0$
0#
0"
0!
$end
#10
1#
#20
0#
1!
1"
#30
1#
#40
0!
0#
0"
1$
#50
1!
1#
#60
0!
0#
1"
#70
1!
1#
