Verilog/DAY5/4_bit_ring_counter/ring_counter_sync/ring_counter.v
module ring_counter (
    input clk,          
    input reset,        
    output reg [3:0] q
);

always @(posedge clk) begin
    if (reset)
        q <= 4'b1000;                
    else
        q <= {q[2:0], q[3]};         
end

endmodule

Verilog/DAY5/4_bit_ring_counter/ring_counter_sync/ring_counter_tb.v
module ring_counter_tb;

    reg clk, reset;
    wire [3:0] q;

    ring_counter uut (
        .clk(clk),
        .reset(reset),
        .q(q)
    );

    initial begin
        clk = 0;
        forever #5 clk = ~clk;
    end

    initial begin
        $dumpfile("ring_counter.vcd");
        $dumpvars(0, ring_counter_tb);

        $monitor("Time=%0t | reset=%b | q=%b", $time, reset, q);


        reset = 1; #10;
        reset = 0; #100;

        $finish;
    end

endmodule

Verilog/DAY5/4_bit_ring_counter/ring_counter_sync/ring_counter.vcd
$date
	Tue Sep 16 06:00:47 2025
$end
$version
	Icarus Verilog
$end
$timescale
	1s
$end
$scope module ring_counter_tb $end
$var wire 4 ! q [3:0] $end
$var reg 1 " clk $end
$var reg 1 # reset $end
$scope module uut $end
$var wire 1 " clk $end
$var wire 1 # reset $end
$var reg 4 $ q [3:0] $end
$upscope $end
$upscope $end
$enddefinitions $end
$comment Show the parameter values. $end
$dumpall
$end
#0
$dumpvars
bx $
1#
0"
bx !
$end
#5
b1000 !
b1000 $
1"
#10
0"
0#
#15
b1 !
b1 $
1"
#20
0"
#25
b10 !
b10 $
1"
#30
0"
#35
b100 !
b100 $
1"
#40
0"
#45
b1000 !
b1000 $
1"
#50
0"
#55
b1 !
b1 $
1"
#60
0"
#65
b10 !
b10 $
1"
#70
0"
#75
b100 !
b100 $
1"
#80
0"
#85
b1000 !
b1000 $
1"
#90
0"
#95
b1 !
b1 $
1"
#100
0"
#105
b10 !
b10 $
1"
