Verilog/ASSIGNMENTS/ASSIGNMENT_5/E. Conditional Statements/39)4bit_counter/counter_sync.v
module counter_sync(
	input  wire        clk,
	input  wire        rst,
	output reg  [3:0]  q 
);
	always @(posedge clk) begin
		if (rst) begin
			q <= 4'b0000;
		end else begin
			q <= q + 1'b1;
		end
	end

endmodule

Verilog/ASSIGNMENTS/ASSIGNMENT_5/E. Conditional Statements/39)4bit_counter/tb_counter_sync.v
module tb_counter_sync;
	reg clk;
	reg rst;
	wire [3:0] q;
	counter_sync uut (
		.clk(clk),
      		.rst(rst),
		.q(q)
	);
	initial begin
		clk = 0;
		forever #5 clk = ~clk;
	end
	initial begin
		$display("\n--- 4-bit synchronous reset counter test ---\n");
		$monitor("%0t | clk=%b rst=%b -> q=%b (%0d)", $time, clk, rst, q, q);

		rst = 1;
		#12;
		rst = 0;
		#100;
		rst = 1;
		#10;
		rst = 0;
		#40;
		$display("\nTest finished\n");
		$finish;
	end
	initial begin
		$dumpfile("counter_sync.vcd");
		$dumpvars(0, tb_counter_sync);
	end

endmodule

Verilog/ASSIGNMENTS/ASSIGNMENT_5/E. Conditional Statements/39)4bit_counter/counter_sync.vcd
$date
	Thu Sep 11 11:06:33 2025
$end
$version
	Icarus Verilog
$end
$timescale
	1s
$end
$scope module tb_counter_sync $end
$var wire 4 ! q [3:0] $end
$var reg 1 " clk $end
$var reg 1 # rst $end
$scope module uut $end
$var wire 1 " clk $end
$var wire 1 # rst $end
$var reg 4 $ q [3:0] $end
$upscope $end
$upscope $end
$enddefinitions $end
$comment Show the parameter values. $end
$dumpall
$end
#0
$dumpvars
bx $
1#
0"
bx !
$end
#5
b0 !
b0 $
1"
#10
0"
#12
0#
#15
b1 !
b1 $
1"
#20
0"
#25
b10 !
b10 $
1"
#30
0"
#35
b11 !
b11 $
1"
#40
0"
#45
b100 !
b100 $
1"
#50
0"
#55
b101 !
b101 $
1"
#60
0"
#65
b110 !
b110 $
1"
#70
0"
#75
b111 !
b111 $
1"
#80
0"
#85
b1000 !
b1000 $
1"
#90
0"
#95
b1001 !
b1001 $
1"
#100
0"
#105
b1010 !
b1010 $
1"
#110
0"
#112
1#
#115
b0 !
b0 $
1"
#120
0"
#122
0#
#125
b1 !
b1 $
1"
#130
0"
#135
b10 !
b10 $
1"
#140
0"
#145
b11 !
b11 $
1"
#150
0"
#155
b100 !
b100 $
1"
