Verilog/DAY5/4_bit_PISO_register/register_async/piso_async.v
module piso_async (
    input clk,              
    input reset,            
    input load,             
    input [3:0] parallel_in,
    output serial_out       
);

    reg [3:0] shift_reg;

    always @(posedge clk or posedge reset) begin
        if (reset)
            shift_reg <= 4'b0000; 
        else if (load)
            shift_reg <= parallel_in; 
        else
            shift_reg <= {shift_reg[2:0], 1'b0};
    end

    assign serial_out = shift_reg[3];

endmodule

Verilog/DAY5/4_bit_PISO_register/register_async/tb_piso_async.v
module tb_piso_async();

    reg clk, reset, load;
    reg [3:0] parallel_in;
    wire serial_out;

    piso_async uut (
        .clk(clk),
        .reset(reset),
        .load(load),
        .parallel_in(parallel_in),
        .serial_out(serial_out)
    );

    initial begin
        clk = 0;
        forever #5 clk = ~clk;
    end

    initial begin
        $dumpfile("piso_async.vcd");
        $dumpvars(0, tb_piso_async);

        $display("Time\t clk reset load parallel_in serial_out");
        $monitor("%0t\t %b  %b  %b  %b  %b", $time, clk, reset, load, parallel_in, serial_out);

        reset = 1; load = 0; parallel_in = 4'b0000; #7;   
        reset = 0; #3;
        load = 1; parallel_in = 4'b1010; #10;
        load = 0;
	#30;
        reset = 1; #4;
        reset = 0; #6;
	load = 1; parallel_in = 4'b1101; #10;
        load = 0;

        #40;
        $finish;
    end

endmodule

Verilog/DAY5/4_bit_PISO_register/register_async/piso_async.vcd
$date
	Tue Sep 16 07:39:08 2025
$end
$version
	Icarus Verilog
$end
$timescale
	1s
$end
$scope module tb_piso_async $end
$var wire 1 ! serial_out $end
$var reg 1 " clk $end
$var reg 1 # load $end
$var reg 4 $ parallel_in [3:0] $end
$var reg 1 % reset $end
$scope module uut $end
$var wire 1 " clk $end
$var wire 1 # load $end
$var wire 4 & parallel_in [3:0] $end
$var wire 1 % reset $end
$var wire 1 ! serial_out $end
$var reg 4 ' shift_reg [3:0] $end
$upscope $end
$upscope $end
$enddefinitions $end
$comment Show the parameter values. $end
$dumpall
$end
#0
$dumpvars
b0 '
b0 &
1%
b0 $
0#
0"
0!
$end
#5
1"
#7
0%
#10
b1010 $
b1010 &
1#
0"
#15
1!
b1010 '
1"
#20
0"
0#
#25
0!
b100 '
1"
#30
0"
#35
1!
b1000 '
1"
#40
0"
#45
0!
b0 '
1"
#50
0"
1%
#54
0%
#55
1"
#60
0"
b1101 $
b1101 &
1#
#65
1!
b1101 '
1"
#70
0"
0#
#75
b1010 '
1"
#80
0"
#85
0!
b100 '
1"
#90
0"
#95
1!
b1000 '
1"
#100
0"
#105
0!
b0 '
1"
