Verilog/ASSIGNMENTS/Assignment_7/A) TASKS/06. Toggle_signal/toggle.v
module toggle;
	reg clk;  
	integer i;

	task toggle_signal;
		inout reg sig;   
		begin
			sig = ~sig;  
		        #10;         
		end
	endtask
	
	initial begin
		$dumpfile("toggle.vcd");
		$dumpvars(0, toggle);
		
		clk = 0;
		$monitor("Time=%0t | clk=%b", $time, clk);

        	for (i = 0; i < 10; i = i + 1) begin
			toggle_signal(clk);
		end

		#10 $finish;
	end
endmodule

Verilog/ASSIGNMENTS/Assignment_7/A) TASKS/06. Toggle_signal/toggle.vcd
$date
	Wed Sep 17 07:44:26 2025
$end
$version
	Icarus Verilog
$end
$timescale
	1s
$end
$scope module toggle $end
$var reg 1 ! clk $end
$var integer 32 " i [31:0] $end
$scope task toggle_signal $end
$var reg 1 # sig $end
$upscope $end
$upscope $end
$enddefinitions $end
$comment Show the parameter values. $end
$dumpall
$end
#0
$dumpvars
1#
b0 "
0!
$end
#10
0#
b1 "
1!
#20
1#
b10 "
0!
#30
0#
b11 "
1!
#40
1#
b100 "
0!
#50
0#
b101 "
1!
#60
1#
b110 "
0!
#70
0#
b111 "
1!
#80
1#
b1000 "
0!
#90
0#
b1001 "
1!
#100
b1010 "
0!
