Verilog/ASSIGNMENTS/Assignment3/20) 1to4_demux/demux1to4.v
module demux1to4(
  input [1:0] sel,
  input din, en,
  output [3:0] y
);

  assign y[0] = (en & (sel == 2'b00)) ? din : 1'b0;
  assign y[1] = (en & (sel == 2'b01)) ? din : 1'b0;
  assign y[2] = (en & (sel == 2'b10)) ? din : 1'b0;
  assign y[3] = (en & (sel == 2'b11)) ? din : 1'b0;

endmodule

Verilog/ASSIGNMENTS/Assignment3/20) 1to4_demux/demux1to4_tb.v
module demux1to4_tb;
  reg din, en;
  reg [1:0] sel;
  wire [3:0] y;

  demux1to4 uut(
    .din(din),
    .en(en),
    .sel(sel),
    .y(y)
  );

  initial begin
    $dumpfile("Demux1to4.vcd");
    $dumpvars(0, demux1to4_tb);
    
    $display("TIME | en din s1 s0 | y0 y1 y2 y3");
    $monitor("%4t |  %b  %b   %b  %b |  %b  %b  %b  %b", 
              $time, en, din, sel[1], sel[0], y[0], y[1], y[2], y[3]);

    en=0; din=1; sel=2'b00; #10;
    din=1; sel=2'b01; #10;
    din=1; sel=2'b10; #10;
    din=1; sel=2'b11; #10;

    en=1; din=0; sel=2'b00; #10;
    din=0; sel=2'b01; #10;
    din=0; sel=2'b10; #10;
    din=0; sel=2'b11; #10;

    din=1; sel=2'b00; #10;
    din=1; sel=2'b01; #10;
    din=1; sel=2'b10; #10;
    din=1; sel=2'b11; #10;

    $finish;
  end
endmodule

Verilog/ASSIGNMENTS/Assignment3/20) 1to4_demux/Demux1to4.vcd
$date
	Mon Sep  8 23:27:37 2025
$end
$version
	Icarus Verilog
$end
$timescale
	1s
$end
$scope module demux1to4_tb $end
$var wire 4 ! y [3:0] $end
$var reg 1 " din $end
$var reg 1 # en $end
$var reg 2 $ sel [1:0] $end
$scope module uut $end
$var wire 1 " din $end
$var wire 1 # en $end
$var wire 2 % sel [1:0] $end
$var wire 4 & y [3:0] $end
$upscope $end
$upscope $end
$enddefinitions $end
$comment Show the parameter values. $end
$dumpall
$end
#0
$dumpvars
b0 &
b0 %
b0 $
0#
1"
b0 !
$end
#10
b1 $
b1 %
#20
b10 $
b10 %
#30
b11 $
b11 %
#40
b0 $
b0 %
0"
1#
#50
b1 $
b1 %
#60
b10 $
b10 %
#70
b11 $
b11 %
#80
b1 !
b1 &
b0 $
b0 %
1"
#90
b10 !
b10 &
b1 $
b1 %
#100
b100 !
b100 &
b10 $
b10 %
#110
b1000 !
b1000 &
b11 $
b11 %
