Verilog/DAY3/Behavioral Modeling/4to1_mux/mux4to1_beh.v
module mux4to1_beh(
	input i0,    
	input i1,    
	input i2,    
	input i3,    
	input [1:0] sel,
	output reg y
);
	always @(*) begin
	case(sel)
		2'b00: y = i0; 
		2'b01: y = i1; 
		2'b10: y = i2; 
		2'b11: y = i3; 
	endcase
end
endmodule

Verilog/DAY3/Behavioral Modeling/4to1_mux/mux4to1_tb.v
module mux4to1_tb;
	reg i0, i1, i2, i3;
	reg [1:0] sel;
	wire y;
	mux4to1_beh uut (
		.i0(i0),
		.i1(i1),
		.i2(i2),
		.i3(i3),
		.sel(sel),
		 .y(y)
	);
	initial begin
		$dumpfile("mux4to1.vcd");
		$dumpvars(0, mux4to1_tb);
		$monitor("Time=%0t | i0=%b i1=%b i2=%b i3=%b sel=%b | y=%b", $time, i0, i1, i2, i3, sel, y);
		i0=0; i1=0; i2=0; i3=0; sel=2'b00; #10;
		i0=0; i1=1; i2=0; i3=0; sel=2'b01; #10;
		i0=1; i1=0; i2=0; i3=0; sel=2'b10; #10;
		i0=0; i1=0; i2=1; i3=0; sel=2'b11; #10;

		i0=1; i1=1; i2=0; i3=0; sel=2'b00; #10;
	        i0=1; i1=0; i2=1; i3=0; sel=2'b01; #10;
	        i0=0; i1=1; i2=1; i3=1; sel=2'b10; #10;
	        i0=1; i1=0; i2=0; i3=1; sel=2'b11; #10;
		$finish;
	end
	endmodule

Verilog/DAY3/Behavioral Modeling/4to1_mux/mux4to1.vcd
$date
	Tue Sep  9 08:21:28 2025
$end
$version
	Icarus Verilog
$end
$timescale
	1s
$end
$scope module mux4to1_tb $end
$var wire 1 ! y $end
$var reg 1 " i0 $end
$var reg 1 # i1 $end
$var reg 1 $ i2 $end
$var reg 1 % i3 $end
$var reg 2 & sel [1:0] $end
$scope module uut $end
$var wire 1 " i0 $end
$var wire 1 # i1 $end
$var wire 1 $ i2 $end
$var wire 1 % i3 $end
$var wire 2 ' sel [1:0] $end
$var reg 1 ! y $end
$upscope $end
$upscope $end
$enddefinitions $end
$comment Show the parameter values. $end
$dumpall
$end
#0
$dumpvars
b0 '
b0 &
0%
0$
0#
0"
0!
$end
#10
1!
b1 &
b1 '
1#
#20
0!
b10 &
b10 '
0#
1"
#30
b11 &
b11 '
1$
0"
#40
1!
b0 &
b0 '
0$
1#
1"
#50
0!
b1 &
b1 '
1$
0#
#60
1!
b10 &
b10 '
1%
1#
0"
#70
b11 &
b11 '
0$
0#
1"
