Verilog/DAY5/4_bit_SIPO_register/register_async/sipo_async.v
module sipo_async (
    input clk,         
    input reset,       
    input serial_in,   
    output [3:0] parallel_out 
);

    reg [3:0] shift_reg;

    always @(posedge clk or posedge reset) begin
        if (reset)
            shift_reg <= 4'b0000;                 
        else
            shift_reg <= {shift_reg[2:0], serial_in}; 
    end

    assign parallel_out = shift_reg;

endmodule

Verilog/DAY5/4_bit_SIPO_register/register_async/tb_sipo_async.v
module tb_sipo_async();

    reg clk;
    reg reset;
    reg serial_in;
    wire [3:0] parallel_out;

    sipo_async uut (
        .clk(clk),
        .reset(reset),
        .serial_in(serial_in),
        .parallel_out(parallel_out)
    );

    initial begin
        clk = 0;
        forever #5 clk = ~clk; // 10ns period
    end

    initial begin
        $dumpfile("sipo_async.vcd");
        $dumpvars(0, tb_sipo_async);

        $display("Time\t clk reset serial_in parallel_out");
        $monitor("%0t\t %b  %b  %b  %b", $time, clk, reset, serial_in, parallel_out);

        reset = 1; serial_in = 0; #7;   
        reset = 0; #3;                  

        serial_in = 1; #10;
        serial_in = 0; #10;
        serial_in = 1; #10;
        serial_in = 1; #10;

        reset = 1; #4;  
        reset = 0; #6;

        serial_in = 1; #10;
        serial_in = 0; #10;

        #20;
        $finish;
    end

endmodule

Verilog/DAY5/4_bit_SIPO_register/register_async/sipo_async.vcd
$date
	Tue Sep 16 07:10:52 2025
$end
$version
	Icarus Verilog
$end
$timescale
	1s
$end
$scope module tb_sipo_async $end
$var wire 4 ! parallel_out [3:0] $end
$var reg 1 " clk $end
$var reg 1 # reset $end
$var reg 1 $ serial_in $end
$scope module uut $end
$var wire 1 " clk $end
$var wire 4 % parallel_out [3:0] $end
$var wire 1 # reset $end
$var wire 1 $ serial_in $end
$var reg 4 & shift_reg [3:0] $end
$upscope $end
$upscope $end
$enddefinitions $end
$comment Show the parameter values. $end
$dumpall
$end
#0
$dumpvars
b0 &
b0 %
0$
1#
0"
b0 !
$end
#5
1"
#7
0#
#10
1$
0"
#15
b1 !
b1 %
b1 &
1"
#20
0"
0$
#25
b10 !
b10 %
b10 &
1"
#30
0"
1$
#35
b101 !
b101 %
b101 &
1"
#40
0"
#45
b1011 !
b1011 %
b1011 &
1"
#50
b0 !
b0 %
b0 &
0"
1#
#54
0#
#55
b1 !
b1 %
b1 &
1"
#60
0"
#65
b11 !
b11 %
b11 &
1"
#70
0"
0$
#75
b110 !
b110 %
b110 &
1"
#80
0"
#85
b1100 !
b1100 %
b1100 &
1"
#90
0"
#95
b1000 !
b1000 %
b1000 &
1"
