Verilog/ASSIGNMENTS/Assignment_7/A) TASKS/02. Subtraction/sub8.v
module sub8;
	reg  [7:0] a, b;
        reg  [8:0] diff;
	integer i;

	wire [7:0] diff_low8;
	wire       borrow;
	wire signed [8:0] signed_diff;

	assign diff_low8   = diff[7:0];
	assign borrow      = diff[8];
	assign signed_diff = diff;

	task sub8_task;
		input  [7:0] x;
		input  [7:0] y;
		output [8:0] d;
		begin
			d = {1'b0, x} - {1'b0, y};
		end
	endtask

	initial begin
		$dumpfile("sub8.vcd");
		$dumpvars(0, sub8);

		$monitor("Time=%0t : a=%0d b=%0d diff_low8=%0d borrow=%b signed_diff=%0d", $time, a, b, diff_low8, borrow, signed_diff);

		a = 8'd50; b = 8'd20; #1;
		sub8_task(a, b, diff);

		a = 8'd20; b = 8'd50; #1;
		sub8_task(a, b, diff);

		a = 8'd0; b = 8'd1; #1;
		sub8_task(a, b, diff);

		for (i = 0; i < 4; i = i + 1) begin
			a = $random;
			b = $random;
			#1 sub8_task(a, b, diff);
		end
		#1 $finish;
	end
endmodule

Verilog/ASSIGNMENTS/Assignment_7/A) TASKS/02. Subtraction/sub8.vcd
$date
	Wed Sep 17 07:09:19 2025
$end
$version
	Icarus Verilog
$end
$timescale
	1s
$end
$scope module sub8 $end
$var wire 9 ! signed_diff [8:0] $end
$var wire 8 " diff_low8 [7:0] $end
$var wire 1 # borrow $end
$var reg 8 $ a [7:0] $end
$var reg 8 % b [7:0] $end
$var reg 9 & diff [8:0] $end
$var integer 32 ' i [31:0] $end
$scope task sub8_task $end
$var reg 9 ( d [8:0] $end
$var reg 8 ) x [7:0] $end
$var reg 8 * y [7:0] $end
$upscope $end
$upscope $end
$enddefinitions $end
$comment Show the parameter values. $end
$dumpall
$end
#0
$dumpvars
bx *
bx )
bx (
bx '
bx &
b10100 %
b110010 $
x#
bx "
bx !
$end
#1
b11110 "
0#
b110010 %
b10100 $
b11110 !
b11110 &
b11110 (
b10100 *
b110010 )
#2
b11100010 "
1#
b1 %
b0 $
b111100010 !
b111100010 &
b111100010 (
b110010 *
b10100 )
#3
b11111111 "
b10000001 %
b100100 $
b0 '
b111111111 !
b111111111 &
b111111111 (
b1 *
b0 )
#4
b10100011 "
b1100011 %
b1001 $
b1 '
b110100011 !
b110100011 &
b110100011 (
b10000001 *
b100100 )
#5
b10100110 "
b10001101 %
b1101 $
b10 '
b110100110 !
b110100110 &
b110100110 (
b1100011 *
b1001 )
#6
b10000000 "
b10010 %
b1100101 $
b11 '
b110000000 !
b110000000 &
b110000000 (
b10001101 *
b1101 )
#7
b1010011 "
0#
b100 '
b1010011 !
b1010011 &
b1010011 (
b10010 *
b1100101 )
