Verilog/DAY5/4_bit_up_down_counter/counter_async/up_down_counter.v
module up_down_counter (
    input clk,          
    input reset,        
    input up_down,      
    output reg [3:0] count
);

always @(posedge clk or posedge reset) begin
    if (reset)
        count <= 4'b0000;      
    else if (up_down)
        count <= count + 1;    
    else
        count <= count - 1;    
end

endmodule

Verilog/DAY5/4_bit_up_down_counter/up_down_counter_tb.v
module up_down_counter_tb;

	reg clk, reset, up_down;
	wire [3:0] count;

	up_down_counter uut (
		.clk(clk),
     		.reset(reset),
     		.up_down(up_down),
      		.count(count)
  	);

	initial begin
		clk = 0;
		forever #5 clk = ~clk;
  	end

	initial begin
		$dumpfile("up_down_counter.vcd");
    		$dumpvars(0, up_down_counter_tb);

    		$monitor("Time=%0t | reset=%b | up_down=%b | count=%b", $time, reset, up_down, count);

                reset = 1; up_down = 1; #10;
		reset = 0;

		up_down = 1; #80;
		up_down = 0; #80;

		$finish;
	end

endmodule

Verilog/DAY5/4_bit_up_down_counter/up_down_counter.vcd
$date
	Tue Sep 16 03:30:21 2025
$end
$version
	Icarus Verilog
$end
$timescale
	1s
$end
$scope module up_down_counter_tb $end
$var wire 4 ! count [3:0] $end
$var reg 1 " clk $end
$var reg 1 # reset $end
$var reg 1 $ up_down $end
$scope module uut $end
$var wire 1 " clk $end
$var wire 1 # reset $end
$var wire 1 $ up_down $end
$var reg 4 % count [3:0] $end
$upscope $end
$upscope $end
$enddefinitions $end
$comment Show the parameter values. $end
$dumpall
$end
#0
$dumpvars
b0 %
1$
1#
0"
b0 !
$end
#5
1"
#10
0"
0#
#15
b1 !
b1 %
1"
#20
0"
#25
b10 !
b10 %
1"
#30
0"
#35
b11 !
b11 %
1"
#40
0"
#45
b100 !
b100 %
1"
#50
0"
#55
b101 !
b101 %
1"
#60
0"
#65
b110 !
b110 %
1"
#70
0"
#75
b111 !
b111 %
1"
#80
0"
#85
b1000 !
b1000 %
1"
#90
0"
0$
#95
b111 !
b111 %
1"
#100
0"
#105
b110 !
b110 %
1"
#110
0"
#115
b101 !
b101 %
1"
#120
0"
#125
b100 !
b100 %
1"
#130
0"
#135
b11 !
b11 %
1"
#140
0"
#145
b10 !
b10 %
1"
#150
0"
#155
b1 !
b1 %
1"
#160
0"
#165
b0 !
b0 %
1"
