Verilog/ASSIGNMENTS/Assignment3/3) sum/adder_delay.v
module adder_delay (a, b, sum);
	input  [3:0] a, b;
	output [4:0] sum;      
	assign #5 sum = a + b;
endmodule

Verilog/ASSIGNMENTS/Assignment3/3) sum/tb_adder_delay.v
module tb_adder_delay;
	reg  [3:0] a, b;
	wire [4:0] sum;

	adder_delay dut (.a(a), .b(b),.sum(sum));

	initial begin
	$dumpfile("adder_delay.vcd");
	$dumpvars(0, tb_adder_delay);
	$display("time)\t a b | sum");
	$monitor("%0t\t %b %b | %b", $time, a, b, sum);
	a = 0;  b = 0;   #10;   
	a = 0;  b = 1;   #10;   
	a = 1;  b = 0;   #10;   
	a = 1; b = 1;   #10;   
	a = 0;  b = 0;   #10;
	$finish;
end
endmodule

Verilog/ASSIGNMENTS/Assignment3/3) sum/adder_delay.vcd
$date
	Mon Sep  8 16:37:49 2025
$end
$version
	Icarus Verilog
$end
$timescale
	1s
$end
$scope module tb_adder_delay $end
$var wire 5 ! sum [4:0] $end
$var reg 4 " a [3:0] $end
$var reg 4 # b [3:0] $end
$scope module dut $end
$var wire 4 $ a [3:0] $end
$var wire 4 % b [3:0] $end
$var wire 5 & sum [4:0] $end
$upscope $end
$upscope $end
$enddefinitions $end
$comment Show the parameter values. $end
$dumpall
$end
#0
$dumpvars
bx &
b0 %
b0 $
b0 #
b0 "
bx !
$end
#5
b0 !
b0 &
#10
b1 #
b1 %
#15
b1 !
b1 &
#20
b0 #
b0 %
b1 "
b1 $
#30
b1 #
b1 %
#35
b10 !
b10 &
#40
b0 #
b0 %
b0 "
b0 $
#45
b0 !
b0 &
